{
  "parent": "minecraft:recipes/root",
  "criteria": {
    "has_the_recipe": {
      "conditions": {
        "recipe": "springnions:golden_onion"
      },
      "trigger": "minecraft:recipe_unlocked"
    },
    "plant_onion": {
      "conditions": {
        "location": [
          {
            "condition": "minecraft:location_check",
            "predicate": {
              "block": {
                "blocks": [
                  "minecraft:farmland"
                ]
              }
            }
          },
          {
            "condition": "minecraft:match_tool",
            "predicate": {
              "items": [
                "springnions:onion"
              ]
            }
          }
        ]
      },
      "trigger": "minecraft:item_used_on_block"
    }
  },
  "requirements": [
    [
      "plant_onion",
      "has_the_recipe"
    ]
  ],
  "rewards": {
    "recipes": [
      "springnions:golden_onion"
    ]
  },
  "sends_telemetry_event": false
}